README.md
setup.py
behavelet/__init__.py
behavelet/morlet.py
behavelet.egg-info/PKG-INFO
behavelet.egg-info/SOURCES.txt
behavelet.egg-info/dependency_links.txt
behavelet.egg-info/not-zip-safe
behavelet.egg-info/requires.txt
behavelet.egg-info/top_level.txt