Metadata-Version: 2.1
Name: behavelet
Version: 0.0.2
Summary: behavelet: a wavelet transform for mapping behavior
Home-page: https://github.com/jgraving/behavelet
Author: Jacob Graving <jgraving@gmail.com>
Author-email: jgraving@gmail.com
Maintainer: Jacob Graving <jgraving@gmail.com>
Maintainer-email: jgraving@gmail.com
License: Apache 2.0
Download-URL: https://github.com/jgraving/behavelet.git
Platform: UNKNOWN
Classifier: Intended Audience :: Science/Research
Classifier: Programming Language :: Python :: 3
